LICENSE
MANIFEST.in
README.rst
setup.py
deferred_filelogger/__init__.py
django_deferred_filelogger.egg-info/PKG-INFO
django_deferred_filelogger.egg-info/SOURCES.txt
django_deferred_filelogger.egg-info/dependency_links.txt
django_deferred_filelogger.egg-info/requires.txt
django_deferred_filelogger.egg-info/top_level.txt