Metadata-Version: 1.0
Name: django-deferred-filelogger
Version: 0.1
Summary: A logging handler for Django that defers evaluation of the filepath
Home-page: https://github.com/codeinthehole/django-deferred-filelogger
Author: David Winterbottom
Author-email: david.winterbottom@gmail.com
License: Copyright (C) 2012 django-deferred-filelogger authors (see AUTHORS file)
